{
  "updated": "2026-06-19T13:47:03Z",
  "items": [
    {
      "id": "https://www.aljazeera.com/news/2026/6/19/british-lawyers-body-suspends-icc-prosecutor-khan-over-misconduct-claim?traffic_source=rss",
      "url": "https://www.aljazeera.com/news/2026/6/19/british-lawyers-body-suspends-icc-prosecutor-khan-over-misconduct-claim?traffic_source=rss",
      "source": "aljazeera",
      "time": 1781874447000,
      "rank": 0,
      "title_ja": "イギリスの弁護士会がICC検察官カーン氏の不正行為疑惑で活動停止処分",
      "summary_ja": "イギリスの法律専門家団体がICC（国際刑事裁判所）のカーン検察官に対して不正行為の疑いで活動停止処分を実施した。これは検察官の職務執行に対する重大な懸念を反映している。",
      "category": "politics",
      "lon": -0.1278,
      "lat": 51.5074,
      "place": "イギリス（ロンドン）"
    },
    {
      "id": "https://www.aljazeera.com/news/2026/6/19/afghanistan-strikes-targets-in-pakistan-raising-cross-border-tension?traffic_source=rss",
      "url": "https://www.aljazeera.com/news/2026/6/19/afghanistan-strikes-targets-in-pakistan-raising-cross-border-tension?traffic_source=rss",
      "source": "aljazeera",
      "time": 1781870261000,
      "rank": 1,
      "title_ja": "アフガニスタンがパキスタン領内の標的を攻撃、越境問題が緊迫化",
      "summary_ja": "アフガニスタンがパキスタン領内の標的に対して軍事攻撃を実施し、両国間の国境地帯での緊張が高まっている。この越境攻撃により、パキスタンとアフガニスタン間の対立が深刻化している。",
      "category": "conflict",
      "lon": 69.2,
      "lat": 34.5,
      "place": "パキスタン・アフガニスタン国境地帯"
    },
    {
      "id": "https://www.aljazeera.com/news/2026/6/19/trump-hints-at-new-approach-to-north-koreas-nuclear-programme?traffic_source=rss",
      "url": "https://www.aljazeera.com/news/2026/6/19/trump-hints-at-new-approach-to-north-koreas-nuclear-programme?traffic_source=rss",
      "source": "aljazeera",
      "time": 1781867243000,
      "rank": 2,
      "title_ja": "トランプ氏、北朝鮮の核計画に対する新たなアプローチを示唆",
      "summary_ja": "トランプ氏が北朝鮮の核問題に対する新たなアプローチを検討していることを示唆した。具体的な政策内容については明らかにされていない。",
      "category": "politics",
      "lon": 125.7652,
      "lat": 39.0163,
      "place": "北朝鮮"
    },
    {
      "id": "https://www.aljazeera.com/features/2026/6/19/can-us-iran-peace-deal-survive-israeli-bombing-of-lebanon?traffic_source=rss",
      "url": "https://www.aljazeera.com/features/2026/6/19/can-us-iran-peace-deal-survive-israeli-bombing-of-lebanon?traffic_source=rss",
      "source": "aljazeera",
      "time": 1781864014000,
      "rank": 3,
      "title_ja": "イスラエルのレバノン爆撃により米国とイランの平和「合意」は生き残れるか？",
      "summary_ja": "イスラエルによるレバノンへの爆撃がエスカレートする中、米国とイランの和平交渉の行方が不透明になっている。この軍事的緊張が中東地域の政治的安定に影響を与える可能性がある。",
      "category": "conflict",
      "lon": 35.8623,
      "lat": 33.8547,
      "place": "レバノン"
    },
    {
      "id": "https://www.aljazeera.com/video/newsfeed/2026/6/19/israel-continues-attacks-on-lebanon-despite-us-iran-deal?traffic_source=rss",
      "url": "https://www.aljazeera.com/video/newsfeed/2026/6/19/israel-continues-attacks-on-lebanon-despite-us-iran-deal?traffic_source=rss",
      "source": "aljazeera",
      "time": 1781862898000,
      "rank": 4,
      "title_ja": "イスラエル、米・イラン協議にもかかわらずレバノンへの攻撃を継続",
      "summary_ja": "イスラエルは米国とイランの間で進む外交協議に関わらず、レバノンに対する軍事攻撃を続けている。地域の緊張が継続している。",
      "category": "conflict",
      "lon": 35.8623,
      "lat": 33.8547,
      "place": "レバノン"
    },
    {
      "id": "https://www.aljazeera.com/news/2026/6/19/us-iran-talks-postponed-as-israel-attacks-lebanon?traffic_source=rss",
      "url": "https://www.aljazeera.com/news/2026/6/19/us-iran-talks-postponed-as-israel-attacks-lebanon?traffic_source=rss",
      "source": "aljazeera",
      "time": 1781852763000,
      "rank": 5,
      "title_ja": "イスラエルのレバノン攻撃により米国とイランの協議が延期",
      "summary_ja": "イスラエルがレバノンに対する攻撃を実施したため、米国とイランの予定されていた協議が延期された。地域の緊張が高まる中での重要な外交日程の変更となっている。",
      "category": "conflict",
      "lon": 35.8623,
      "lat": 33.8547,
      "place": "レバノン"
    },
    {
      "id": "https://www.aljazeera.com/news/2026/6/19/iran-war-day-112-vance-defends-tehran-deal-but-switzerland-trips-are-off?traffic_source=rss",
      "url": "https://www.aljazeera.com/news/2026/6/19/iran-war-day-112-vance-defends-tehran-deal-but-switzerland-trips-are-off?traffic_source=rss",
      "source": "aljazeera",
      "time": 1781849040000,
      "rank": 6,
      "title_ja": "イラン戦争112日目：ヴァンスがテヘラン「取引」を擁護、スイス訪問は中止",
      "summary_ja": "米国のヴァンス氏がイランとの取引を擁護する一方で、スイスへの訪問が中止となった。イラン情勢は引き続き緊迫した状態が続いている。",
      "category": "conflict",
      "lon": 53.688,
      "lat": 32.4279,
      "place": "イラン"
    },
    {
      "id": "https://www.bbc.com/news/articles/cy735xlv50ko?at_medium=RSS&at_campaign=rss",
      "url": "https://www.bbc.com/news/articles/cy735xlv50ko?at_medium=RSS&at_campaign=rss",
      "source": "bbcworld",
      "time": 1781847239000,
      "rank": 9,
      "title_ja": "米国とイスラエルのイラン戦争で数千人が殺害 - 専門家は真の犠牲者数は判明しないと指摘",
      "summary_ja": "米国とイスラエルによるイラン関連の軍事行動で数千人が殺害されたと報じられている。専門家らは、実際の犠牲者数がどれだけ正確に判明するかは不確実だと述べている。",
      "category": "conflict",
      "lon": 53.688,
      "lat": 32.4279,
      "place": "イラン"
    },
    {
      "id": "https://www.bbc.com/news/articles/c74ynmnrwmeo?at_medium=RSS&at_campaign=rss",
      "url": "https://www.bbc.com/news/articles/c74ynmnrwmeo?at_medium=RSS&at_campaign=rss",
      "source": "bbcworld",
      "time": 1781792202000,
      "rank": 11,
      "title_ja": "兵器、資金、船舶：今回のイラン取引は過去と何が異なるのか",
      "summary_ja": "イランとの最新の取引について、兵器、資金、船舶など複数の要素を含む内容とその過去の取引との違いを解説している。",
      "category": "politics",
      "lon": 53.688,
      "lat": 32.4279,
      "place": "イラン"
    },
    {
      "id": "https://www.theguardian.com/world/live/2026/jun/19/middle-east-crisis-live-israel-strikes-targets-in-lebanon-as-us-iran-talks-in-switzerland-called-off",
      "url": "https://www.theguardian.com/world/live/2026/jun/19/middle-east-crisis-live-israel-strikes-targets-in-lebanon-as-us-iran-talks-in-switzerland-called-off",
      "source": "guardian",
      "time": 1781875658000,
      "rank": 12,
      "title_ja": "中東危機ライブ：イスラエルがレバノンの標的を攻撃、スイスでの米イラン協議は中止に",
      "summary_ja": "イスラエルがレバノンの標的に対する攻撃を実施している。一方、スイスで予定されていた米国とイランの協議は中止となった。",
      "category": "conflict",
      "lon": 35.8623,
      "lat": 33.8547,
      "place": "レバノン"
    },
    {
      "id": "https://www.theguardian.com/world/2026/jun/19/normal-shipping-will-not-resume-in-strait-of-hormuz-until-mines-cleared",
      "url": "https://www.theguardian.com/world/2026/jun/19/normal-shipping-will-not-resume-in-strait-of-hormuz-until-mines-cleared",
      "source": "guardian",
      "time": 1781874729000,
      "rank": 13,
      "title_ja": "ホルムズ海峡での通常航行再開には80個の機雷除去が必要",
      "summary_ja": "ホルムズ海峡での通常の海運が再開されるには、80個の機雷の除去が必須との見解が示されている。海峡の安全確保が国際海運の重要課題となっている。",
      "category": "conflict",
      "lon": 56.2667,
      "lat": 26.5667,
      "place": "ホルムズ海峡（オマーン・イラン間）"
    },
    {
      "id": "https://www.theguardian.com/world/2026/jun/19/us-iran-talks-in-switzerland-cancelled",
      "url": "https://www.theguardian.com/world/2026/jun/19/us-iran-talks-in-switzerland-cancelled",
      "source": "guardian",
      "time": 1781861702000,
      "rank": 14,
      "title_ja": "スイスでの米国とイラン協議が突然中止、イスラエルとヒズボラがレバノンで攻撃を応酬",
      "summary_ja": "スイスで予定されていた米国とイランの協議が突然中止された。同時にイスラエルとレバノンのヒズボラが相互に攻撃を繰り広げている。",
      "category": "conflict",
      "lon": 35.8623,
      "lat": 33.8547,
      "place": "レバノン"
    },
    {
      "id": "https://www.theguardian.com/world/2026/jun/19/trump-iran-deal-legacy",
      "url": "https://www.theguardian.com/world/2026/jun/19/trump-iran-deal-legacy",
      "source": "guardian",
      "time": 1781856027000,
      "rank": 15,
      "title_ja": "トランプ前大統領のイラン核合意戦略、イランの判断で遺産が左右される可能性",
      "summary_ja": "トランプ前大統領のイラン政策が今後、テヘランの決定に大きく影響される可能性が指摘されている。核合意に関する彼の政治的遺産がイランの対応次第で変わる見込み。",
      "category": "politics",
      "lon": 51.3889,
      "lat": 35.6892,
      "place": "イラン・テヘラン"
    },
    {
      "id": "https://www.theguardian.com/us-news/2026/jun/19/first-thing-us-iran-peace-talks-cancelled-israeli-strikes-lebanon",
      "url": "https://www.theguardian.com/us-news/2026/jun/19/first-thing-us-iran-peace-talks-cancelled-israeli-strikes-lebanon",
      "source": "guardian",
      "time": 1781873181000,
      "rank": 16,
      "title_ja": "米国とイランの平和交渉が突然中止、レバノンでのイスラエルの新たな攻撃の最中",
      "summary_ja": "米国とイランの平和交渉が予期せず中止となった。この決定はレバノンにおけるイスラエルによる新たな軍事攻撃が再開される中で発表された。",
      "category": "conflict",
      "lon": 35.8623,
      "lat": 33.8547,
      "place": "レバノン"
    },
    {
      "id": "https://www.dw.com/en/us-iran-talks-hope-and-skepticism-in-the-swiss-alps/a-77610766?maca=en-rss-en-world-4025-rdf",
      "url": "https://www.dw.com/en/us-iran-talks-hope-and-skepticism-in-the-swiss-alps/a-77610766?maca=en-rss-en-world-4025-rdf",
      "source": "dw",
      "time": 1781791920000,
      "rank": 20,
      "title_ja": "米国とイラン協議：スイスアルプスでの希望と懐疑",
      "summary_ja": "米国とイランがスイスアルプスで対話を行い、核問題などについて協議している。交渉の成功に向けて期待がある一方で、懐疑的な見方も存在する。",
      "category": "politics",
      "lon": 8.2275,
      "lat": 46.8182,
      "place": "スイス・アルプス地域"
    },
    {
      "id": "https://www.france24.com/en/uncertainty-remains-amid-postponed-us-iran-talks-and-continued-fighting-in-lebanon",
      "url": "https://www.france24.com/en/uncertainty-remains-amid-postponed-us-iran-talks-and-continued-fighting-in-lebanon",
      "source": "france24",
      "time": 1781874240000,
      "rank": 22,
      "title_ja": "米国とイランの協議延期と、レバノンでの戦闘継続の中で不確実性が残存",
      "summary_ja": "米国とイランの核協議が延期され、レバノンではイスラエルとヒズボラの戦闘が継続している。地域の緊張が高まる中、和平への道筋が不透明な状況が続いている。",
      "category": "conflict",
      "lon": 35.8623,
      "lat": 33.8547,
      "place": "レバノン"
    },
    {
      "id": "https://www.france24.com/en/video/20260619-israeli-military-strikes-southern-lebanon-as-us-iran-talks-are-postponed",
      "url": "https://www.france24.com/en/video/20260619-israeli-military-strikes-southern-lebanon-as-us-iran-talks-are-postponed",
      "source": "france24",
      "time": 1781866523000,
      "rank": 23,
      "title_ja": "イスラエル軍が南レバノンを空爆、米国・イラン協議は延期",
      "summary_ja": "イスラエル軍が南レバノンへの軍事作戦を実施している。同時に米国とイランの協議が延期されている。",
      "category": "conflict",
      "lon": 35.5,
      "lat": 33.2,
      "place": "レバノン南部"
    },
    {
      "id": "https://www.france24.com/en/eu-leaders-discuss-ukraine-membership-and-next-multi-billion-euro-budget",
      "url": "https://www.france24.com/en/eu-leaders-discuss-ukraine-membership-and-next-multi-billion-euro-budget",
      "source": "france24",
      "time": 1781866370000,
      "rank": 24,
      "title_ja": "EU指導者、ウクライナ加盟とEU次期予算について協議",
      "summary_ja": "EU指導者がウクライナの欧州連合加盟と、数十億ユーロ規模の次期予算について議論を行った。EUの拡大とその財政計画が主要議題となった。",
      "category": "politics",
      "lon": 4.3517,
      "lat": 50.8503,
      "place": "ベルギー（ブリュッセル）"
    },
    {
      "id": "https://www.france24.com/en/israel-steps-up-attacks-in-lebanon-amid-fallout-with-us-over-iran-deal",
      "url": "https://www.france24.com/en/israel-steps-up-attacks-in-lebanon-amid-fallout-with-us-over-iran-deal",
      "source": "france24",
      "time": 1781861279000,
      "rank": 25,
      "title_ja": "イランの核合意をめぐる米国との対立の中、イスラエルがレバノンへの攻撃を強化",
      "summary_ja": "イランの核合意問題をめぐってアメリカとの関係が悪化する中、イスラエルはレバノンに対する軍事攻撃を激化させている。この地域の緊張がさらに高まっている。",
      "category": "conflict",
      "lon": 35.8623,
      "lat": 33.8547,
      "place": "レバノン"
    }
  ]
}