[{"name":"Budapest","name_ja":"ブダペスト","lon":19.081375,"lat":47.501952,"pop":1679000,"qid":"Q1781"},{"name":"Miskolc","name_ja":"ミシュコルツ","lon":20.780013,"lat":48.100409,"pop":247757,"qid":"Q102397"},{"name":"Debrecen","name_ja":"デブレツェン","lon":21.630039,"lat":47.53047,"pop":231286,"qid":"Q79880"},{"name":"Szeged","name_ja":"セゲド","lon":20.150026,"lat":46.250393,"pop":187765,"qid":"Q81581"},{"name":"Pécs","name_ja":"ペーチ","lon":18.220014,"lat":46.080429,"pop":186262,"qid":"Q45779"},{"name":"Nyíregyháza","name_ja":"ニーレジハーザ","lon":21.718715,"lat":47.965327,"pop":176880,"qid":"Q171223"},{"name":"Székesfehérvár","name_ja":"セーケシュフェヘールヴァール","lon":18.408065,"lat":47.194676,"pop":144319,"qid":"Q130212"},{"name":"Győr","name_ja":"ジェール","lon":17.630024,"lat":47.700356,"pop":136081,"qid":"Q134494"},{"name":"Kecskemét","name_ja":"ケチケメート","lon":19.700027,"lat":46.900043,"pop":113895,"qid":"Q171357"},{"name":"Szombathely","name_ja":"ソンバトヘイ","lon":16.628742,"lat":47.225346,"pop":109518,"qid":"Q42007"},{"name":"Szolnok","name_ja":"ソルノク","lon":20.179378,"lat":47.186356,"pop":109261,"qid":"Q181276"},{"name":"Kaposvár","name_ja":"カポシュヴァール","lon":17.799988,"lat":46.367026,"pop":108528,"qid":"Q184998"},{"name":"Tatabánya","name_ja":"タタバーニャ","lon":18.433,"lat":47.549997,"pop":70541,"qid":"Q187821"},{"name":"Békéscsaba","name_ja":"ベーケーシュチャバ","lon":21.101005,"lat":46.672002,"pop":65206,"qid":"Q178878"},{"name":"Veszprém","name_ja":"ヴェスプレーム","lon":17.911,"lat":47.090997,"pop":62023,"qid":"Q146317"},{"name":"Zalaegerszeg","name_ja":"ザラエゲルセグ","lon":16.84,"lat":46.844001,"pop":61898,"qid":"Q60037"},{"name":"Eger","name_ja":"エゲル","lon":20.383003,"lat":47.895003,"pop":56647,"qid":"Q167109"},{"name":"Salgótarján","name_ja":"シャルゴータルヤーン","lon":19.826002,"lat":48.105,"pop":39640,"qid":"Q189769"},{"name":"Vác","name_ja":"ヴァーチ","lon":19.13324,"lat":47.783658,"pop":35293,"qid":"Q207408"},{"name":"Szekszárd","name_ja":"セクサールド","lon":18.712999,"lat":46.343997,"pop":34174,"qid":"Q189761"}]