[{"name":"Baghdad","name_ja":"バグダード","lon":44.391923,"lat":33.340594,"pop":5054000},{"name":"Mosul","name_ja":"モースル","lon":43.143059,"lat":36.346948,"pop":1316000},{"name":"Duhok","name_ja":"ドホーク","lon":43.000003,"lat":36.8667,"pop":986000},{"name":"Irbil","name_ja":"アルビール","lon":44.006675,"lat":36.18099,"pop":926000},{"name":"Basra","name_ja":"バスラ","lon":47.811611,"lat":30.51547,"pop":870000},{"name":"As Sulaymaniyah","name_ja":"スレイマニヤ","lon":45.43086,"lat":35.561278,"pop":723170},{"name":"Najaf","name_ja":"ナジャフ","lon":44.335371,"lat":32.000332,"pop":665552},{"name":"Kirkuk","name_ja":"キルクーク","lon":44.392267,"lat":35.472239,"pop":601433},{"name":"Al Hillah","name_ja":"ヒッラ","lon":44.421722,"lat":32.472138,"pop":594605},{"name":"Karbala","name_ja":"カルバラー","lon":44.024486,"lat":32.61492,"pop":510692},{"name":"An Nasiriyah","name_ja":"ナーシリーヤ","lon":46.267553,"lat":31.042949,"pop":451547},{"name":"Ad Diwaniyah","name_ja":"ディーワーニーヤ","lon":44.923966,"lat":31.988938,"pop":358408},{"name":"Al Amarah","name_ja":"アマーラ","lon":47.151168,"lat":31.841608,"pop":345007},{"name":"Al Kut","name_ja":"クート","lon":45.83037,"lat":32.490716,"pop":321521},{"name":"Baqubah","name_ja":"バアクーバ","lon":44.657263,"lat":33.747642,"pop":299479},{"name":"Ar Ramadi","name_ja":"ラマーディー","lon":43.299982,"lat":33.420013,"pop":295121},{"name":"Az Aubayr","name_ja":"ズバイル","lon":47.707982,"lat":30.389164,"pop":262219},{"name":"Al Fallujah","name_ja":"ファルージャ","lon":43.777266,"lat":33.347666,"pop":231819},{"name":"As Samawah","name_ja":"サマーワ","lon":45.280275,"lat":31.309858,"pop":174978},{"name":"Ash Shatrah","name_ja":"アシュ・シャトラ","lon":46.177222,"lat":31.417525,"pop":161949},{"name":"Samarra","name_ja":"サーマッラー","lon":43.875001,"lat":34.193997,"pop":158508},{"name":"Tall Afar","name_ja":"タル・アファル","lon":42.44975,"lat":36.375982,"pop":144465},{"name":"Zakho","name_ja":"ザーホー","lon":42.687203,"lat":37.14454,"pop":134863},{"name":"Al Musayyib","name_ja":"ムサイーブ","lon":44.289999,"lat":32.778631,"pop":76454},{"name":"Tikrit","name_ja":"ティクリート","lon":43.676962,"lat":34.597047,"pop":56591},{"name":"Mandali","name_ja":"マンダリ","lon":45.546357,"lat":33.743611,"pop":29785},{"name":"Ar Rutbah","name_ja":"ルトバ","lon":40.284455,"lat":33.03846,"pop":22370}]