[{"name":"Belgrade","name_ja":"ベオグラード","lon":20.466045,"lat":44.820591,"pop":1099000,"qid":"Q3711"},{"name":"Niš","name_ja":"ニシュ","lon":21.899996,"lat":43.330416,"pop":250000,"qid":"Q129259"},{"name":"Novi Sad","name_ja":"ノヴィ・サド","lon":19.849941,"lat":45.250376,"pop":225457,"qid":"Q55630"},{"name":"Kragujevac","name_ja":"クラグイェヴァツ","lon":20.920004,"lat":44.01996,"pop":171197,"qid":"Q167394"},{"name":"Čačak","name_ja":"チャチャク","lon":20.330118,"lat":43.889736,"pop":170000,"qid":"Q208038"},{"name":"Subotica","name_ja":"スボティツァ","lon":19.680028,"lat":46.070016,"pop":100000,"qid":"Q170287"},{"name":"Zrenjanin","name_ja":"ズレニャニン","lon":20.399468,"lat":45.378637,"pop":64053,"qid":"Q201125"}]